PythonLinearNonlinearControl/__init__.py
PythonLinearNonlinearControl/helper.py
PythonLinearNonlinearControl/common/__init__.py
PythonLinearNonlinearControl/common/utils.py
PythonLinearNonlinearControl/configs/__init__.py
PythonLinearNonlinearControl/configs/cartpole.py
PythonLinearNonlinearControl/configs/first_order_lag.py
PythonLinearNonlinearControl/configs/make_configs.py
PythonLinearNonlinearControl/configs/nonlinear_sample_system.py
PythonLinearNonlinearControl/configs/two_wheeled.py
PythonLinearNonlinearControl/controllers/__init__.py
PythonLinearNonlinearControl/controllers/cem.py
PythonLinearNonlinearControl/controllers/controller.py
PythonLinearNonlinearControl/controllers/ddp.py
PythonLinearNonlinearControl/controllers/ilqr.py
PythonLinearNonlinearControl/controllers/make_controllers.py
PythonLinearNonlinearControl/controllers/mpc.py
PythonLinearNonlinearControl/controllers/mppi.py
PythonLinearNonlinearControl/controllers/mppi_williams.py
PythonLinearNonlinearControl/controllers/nmpc.py
PythonLinearNonlinearControl/controllers/nmpc_cgmres.py
PythonLinearNonlinearControl/controllers/random.py
PythonLinearNonlinearControl/envs/__init__.py
PythonLinearNonlinearControl/envs/cartpole.py
PythonLinearNonlinearControl/envs/cost.py
PythonLinearNonlinearControl/envs/env.py
PythonLinearNonlinearControl/envs/first_order_lag.py
PythonLinearNonlinearControl/envs/make_envs.py
PythonLinearNonlinearControl/envs/nonlinear_sample_system.py
PythonLinearNonlinearControl/envs/two_wheeled.py
PythonLinearNonlinearControl/models/__init__.py
PythonLinearNonlinearControl/models/cartpole.py
PythonLinearNonlinearControl/models/first_order_lag.py
PythonLinearNonlinearControl/models/make_models.py
PythonLinearNonlinearControl/models/model.py
PythonLinearNonlinearControl/models/nonlinear_sample_system.py
PythonLinearNonlinearControl/models/two_wheeled.py
PythonLinearNonlinearControl/planners/__init__.py
PythonLinearNonlinearControl/planners/closest_point_planner.py
PythonLinearNonlinearControl-2.0.dist-info/METADATA
PythonLinearNonlinearControl-2.0.dist-info/WHEEL
PythonLinearNonlinearControl-2.0.dist-info/top_level.txt
PythonLinearNonlinearControl-2.0.dist-info/RECORD
